LICENSE
README.md
pyproject.toml
setup.py
coperception/__init__.py
coperception.egg-info/PKG-INFO
coperception.egg-info/SOURCES.txt
coperception.egg-info/dependency_links.txt
coperception.egg-info/requires.txt
coperception.egg-info/top_level.txt
coperception/configs/Config.py
coperception/configs/ConfigGlobal.py
coperception/configs/__init__.py
coperception/datasets/NuscenesDataset.py
coperception/datasets/V2XSimDet.py
coperception/datasets/V2XSimSeg.py
coperception/datasets/__init__.py
coperception/models/__init__.py
coperception/models/det/AgentWiseWeightedFusion.py
coperception/models/det/CatFusion.py
coperception/models/det/DiscoNet.py
coperception/models/det/FaFNet.py
coperception/models/det/MaxFusion.py
coperception/models/det/MeanFusion.py
coperception/models/det/SumFusion.py
coperception/models/det/TeacherNet.py
coperception/models/det/V2VNet.py
coperception/models/det/When2com.py
coperception/models/det/__init__.py
coperception/models/det/backbone/Backbone.py
coperception/models/det/backbone/__init__.py
coperception/models/det/base/DetModelBase.py
coperception/models/det/base/FusionBase.py
coperception/models/det/base/IntermediateModelBase.py
coperception/models/det/base/NonIntermediateModelBase.py
coperception/models/det/base/__init__.py
coperception/models/seg/AgentWiseWeightedFusion.py
coperception/models/seg/CatFusion.py
coperception/models/seg/DiscoNet.py
coperception/models/seg/FusionBase.py
coperception/models/seg/MaxFusion.py
coperception/models/seg/MeanFusion.py
coperception/models/seg/SegModelBase.py
coperception/models/seg/SumFusion.py
coperception/models/seg/UNet.py
coperception/models/seg/V2VNet.py
coperception/models/seg/When2Com_UNet.py
coperception/models/seg/__init__.py
coperception/utils/AverageMeter.py
coperception/utils/CoDetModule.py
coperception/utils/SegMetrics.py
coperception/utils/SegModule.py
coperception/utils/__init__.py
coperception/utils/data_util.py
coperception/utils/detection_util.py
coperception/utils/loss.py
coperception/utils/mean_ap.py
coperception/utils/min_norm_solvers.py
coperception/utils/nuscenes_pc_util.py
coperception/utils/obj_util.py
coperception/utils/postprocess.py
